red2df/__init__.py
red2df-1.1.0.dist-info/LICENSE.txt
red2df-1.1.0.dist-info/METADATA
red2df-1.1.0.dist-info/WHEEL
red2df-1.1.0.dist-info/top_level.txt
red2df-1.1.0.dist-info/RECORD
